midi2poprap.py
midi2poprap-1.0.3.dist-info/METADATA
midi2poprap-1.0.3.dist-info/WHEEL
midi2poprap-1.0.3.dist-info/top_level.txt
midi2poprap-1.0.3.dist-info/RECORD
